LICENSE
MANIFEST.in
README.md
pyproject.toml
setup.py
cbpi4gui/__init__.py
cbpi4gui/config.yaml
cbpi4gui/version.py
cbpi4gui.egg-info/PKG-INFO
cbpi4gui.egg-info/SOURCES.txt
cbpi4gui.egg-info/dependency_links.txt
cbpi4gui.egg-info/top_level.txt
cbpi4gui/build/asset-manifest.json
cbpi4gui/build/favicon.ico
cbpi4gui/build/index.html
cbpi4gui/build/logo192.png
cbpi4gui/build/logo512.png
cbpi4gui/build/manifest.json
cbpi4gui/build/paypal.png
cbpi4gui/build/robots.txt
cbpi4gui/build/static/css/main.814ce619.css
cbpi4gui/build/static/js/main.65b608fc.js
cbpi4gui/build/static/js/main.65b608fc.js.LICENSE.txt
cbpi4gui/build/static/media/Reacticon.62b41405c3951389251c.png
cbpi4gui/build/static/media/buzzer.4d5932be5f2519107768.mp3
cbpi4gui/build/static/media/cbpi.f1a4ae594af1e1df335b.png
cbpi4gui/build/static/media/cbpi_no_border.5446caa7c8efc97bdcc1.png
cbpi4gui/build/static/media/kettle.77e9dd6425b5f8f52bbf9fb5e82777c0.svg
cbpi4gui/build/static/media/tank2.891ce17091e46c74c1157a9c7013ea70.svg