Metadata-Version: 2.4
Name: cbpi4gui
Version: 0.5.0
Summary: CraftBeerPi4 User Interface
Home-page: https://openbrewing.gitbook.io/craftbeerpi4_support/
Author: Manuel Fritsch / Alexander Vollkopf
Author-email: avollkopf@web.de
License-File: LICENSE
Dynamic: author
Dynamic: author-email
Dynamic: description
Dynamic: description-content-type
Dynamic: home-page
Dynamic: license-file
Dynamic: summary
